// class version 61.0 (61)
// access flags 0x21
public class foundationgames/chasmix/test/resources/targets/MethodTestTarget implements foundationgames/chasmix/test/resources/TestDuckInterface {

  // compiled from: MethodTestTarget.java
  // access flags 0x19
  public final static INNERCLASS java/lang/invoke/MethodHandles$Lookup java/lang/invoke/MethodHandles Lookup

  // access flags 0x19
  public final static Ljava/lang/String; CONSTANT = "A Constant String"

  // access flags 0x2
  private newMethod()V
   L0
    LINENUMBER 13 L0
    ALOAD 0
    LDC "Foo"
    INVOKEVIRTUAL foundationgames/chasmix/test/resources/targets/MethodTestTarget.privateInstanceMethod (Ljava/lang/Object;)V
   L1
    LINENUMBER 14 L1
    INVOKESTATIC foundationgames/chasmix/test/resources/targets/MethodTestTarget.newStaticMethod ()V
   L2
    LINENUMBER 16 L2
    ALOAD 0
    CHECKCAST foundationgames/chasmix/test/resources/targets/MethodTestTarget
    INVOKEVIRTUAL foundationgames/chasmix/test/resources/targets/MethodTestTarget.instanceMethod ()V
   L3
    LINENUMBER 17 L3
    RETURN
   L4
    LOCALVARIABLE this Lfoundationgames/chasmix/test/resources/mixin/TestMethodMerging; L0 L4 0
    MAXSTACK = 2
    MAXLOCALS = 1

  // access flags 0xA
  private static newStaticMethod()V
   L0
    LINENUMBER 20 L0
    GETSTATIC java/lang/System.out : Ljava/io/PrintStream;
    LDC "New Static Method"
    INVOKEVIRTUAL java/io/PrintStream.println (Ljava/lang/String;)V
   L1
    LINENUMBER 21 L1
    RETURN
    MAXSTACK = 2
    MAXLOCALS = 0

  // access flags 0x1
  public quack(Z)V
    // parameter  P0
   L0
    LINENUMBER 25 L0
    GETSTATIC java/lang/System.out : Ljava/io/PrintStream;
    LDC "Quack"
    INVOKEVIRTUAL java/io/PrintStream.println (Ljava/lang/String;)V
   L1
    LINENUMBER 27 L1
    ILOAD 1
    IFEQ L2
   L3
    LINENUMBER 28 L3
    ALOAD 0
    INVOKEVIRTUAL foundationgames/chasmix/test/resources/targets/MethodTestTarget.newMethod ()V
   L2
    LINENUMBER 30 L2
   FRAME SAME
    RETURN
   L4
    LOCALVARIABLE this Lfoundationgames/chasmix/test/resources/mixin/TestMethodMerging; L0 L4 0
    LOCALVARIABLE loudly Z L0 L4 1
    MAXSTACK = 2
    MAXLOCALS = 2

  // access flags 0x1
  public <init>()V
   L0
    LINENUMBER 3 L0
    ALOAD 0
    INVOKESPECIAL java/lang/Object.<init> ()V
    RETURN
   L1
    LOCALVARIABLE this Lfoundationgames/chasmix/test/resources/targets/MethodTestTarget; L0 L1 0
    MAXSTACK = 1
    MAXLOCALS = 1

  // access flags 0x9
  public static staticMethod([I)I
    // parameter  P0
   L0
    LINENUMBER 7 L0
    ICONST_0
    ISTORE 1
   L1
    LINENUMBER 8 L1
    ALOAD 0
    ASTORE 2
    ALOAD 2
    ARRAYLENGTH
    ISTORE 3
    ICONST_0
    ISTORE 4
   L2
   FRAME FULL [[I I [I I I] []
    ILOAD 4
    ILOAD 3
    IF_ICMPGE L3
    ALOAD 2
    ILOAD 4
    IALOAD
    ISTORE 5
   L4
    LINENUMBER 9 L4
    ILOAD 1
    ILOAD 5
    IADD
    ISTORE 1
   L5
    LINENUMBER 8 L5
    IINC 4 1
    GOTO L2
   L3
    LINENUMBER 12 L3
   FRAME SAME
    ILOAD 1
    IRETURN
   L6
    LOCALVARIABLE x I L4 L5 5
    LOCALVARIABLE array [I L0 L6 0
    LOCALVARIABLE result I L1 L6 1
    MAXSTACK = 2
    MAXLOCALS = 6

  // access flags 0x1
  public instanceMethod()V
   L0
    LINENUMBER 16 L0
    GETSTATIC java/lang/System.out : Ljava/io/PrintStream;
    LDC "Hello from Instance"
    INVOKEVIRTUAL java/io/PrintStream.println (Ljava/lang/String;)V
   L1
    LINENUMBER 17 L1
    RETURN
   L2
    LOCALVARIABLE this Lfoundationgames/chasmix/test/resources/targets/MethodTestTarget; L0 L2 0
    MAXSTACK = 2
    MAXLOCALS = 1

  // access flags 0x2
  private privateInstanceMethod(Ljava/lang/Object;)V
    // parameter  P0
   L0
    LINENUMBER 20 L0
    GETSTATIC java/lang/System.out : Ljava/io/PrintStream;
    ALOAD 1
    INVOKEDYNAMIC makeConcatWithConstants(Ljava/lang/Object;)Ljava/lang/String; [
      // handle kind 0x6 : INVOKESTATIC
      java/lang/invoke/StringConcatFactory.makeConcatWithConstants(Ljava/lang/invoke/MethodHandles$Lookup;Ljava/lang/String;Ljava/lang/invoke/MethodType;Ljava/lang/String;[Ljava/lang/Object;)Ljava/lang/invoke/CallSite;
      // arguments:
      "Private Hello from Instance: \u0001"
    ]
    INVOKEVIRTUAL java/io/PrintStream.println (Ljava/lang/String;)V
   L1
    LINENUMBER 21 L1
    RETURN
   L2
    LOCALVARIABLE this Lfoundationgames/chasmix/test/resources/targets/MethodTestTarget; L0 L2 0
    LOCALVARIABLE value Ljava/lang/Object; L0 L2 1
    MAXSTACK = 2
    MAXLOCALS = 2

  // access flags 0x8
  static <clinit>()V
   L0
    LINENUMBER 24 L0
    ICONST_0
    ISTORE 0
   L1
   FRAME APPEND [I]
    ILOAD 0
    ICONST_5
    IF_ICMPGE L2
   L3
    LINENUMBER 25 L3
    GETSTATIC java/lang/System.out : Ljava/io/PrintStream;
    LDC "A Constant String"
    INVOKEVIRTUAL java/io/PrintStream.println (Ljava/lang/String;)V
   L4
    LINENUMBER 24 L4
    IINC 0 1
    GOTO L1
   L2
    LINENUMBER 27 L2
   FRAME SAME
    RETURN
    LOCALVARIABLE i I L1 L2 0
    MAXSTACK = 2
    MAXLOCALS = 1
}
